{"name": "BG", "children": [{"name": "Words", "children": [{"name": "NOUN", "children": [{"name": "rock", "children": [{"name": "rock", "children": [{"similarity": 1.0}]}, {"name": "rocks", "children": [{"similarity": 0.7268403728933546}]}]}, {"name": "circle", "children": [{"name": "circle", "children": [{"similarity": 1.0}]}, {"name": "circles", "children": [{"similarity": 0.797561836745811}]}]}, {"name": "asteroid", "children": [{"name": "asteroid", "children": [{"similarity": 0.9999999999999999}]}, {"name": "comet", "children": [{"similarity": 0.7205527937329798}]}, {"name": "asteroids", "children": [{"similarity": 0.8241148535210703}]}]}, {"name": "comet", "children": [{"name": "asteroid", "children": [{"similarity": 0.7205527937329798}]}, {"name": "comet", "children": [{"similarity": 1.0}]}]}, {"name": "turn", "children": [{"name": "turn", "children": [{"similarity": 1.0}]}, {"name": "way", "children": [{"similarity": 0.7020985376903934}]}]}, {"name": "launch", "children": [{"name": "launch", "children": [{"similarity": 1.0}]}, {"name": "launches", "children": [{"similarity": 0.8175134712756278}]}]}, {"name": "way", "children": [{"name": "turn", "children": [{"similarity": 0.7020985376903934}]}, {"name": "way", "children": [{"similarity": 1.0}]}]}, {"name": "rocks", "children": [{"name": "rock", "children": [{"similarity": 0.7268403728933546}]}, {"name": "rocks", "children": [{"similarity": 0.9999999999999998}]}]}, {"name": "Scientists", "children": [{"name": "Scientists", "children": [{"similarity": 1.0000000000000002}]}, {"name": "Researchers", "children": [{"similarity": 0.8457832959005263}]}]}, {"name": "asteroids", "children": [{"name": "asteroid", "children": [{"similarity": 0.8241148535210703}]}, {"name": "asteroids", "children": [{"similarity": 1.0}]}]}, {"name": "Researchers", "children": [{"name": "Scientists", "children": [{"similarity": 0.8457832959005263}]}, {"name": "Researchers", "children": [{"similarity": 1.0}]}]}, {"name": "launches", "children": [{"name": "launch", "children": [{"similarity": 0.8175134712756278}]}, {"name": "launches", "children": [{"similarity": 1.0000000000000002}]}]}, {"name": "circles", "children": [{"name": "circle", "children": [{"similarity": 0.797561836745811}]}, {"name": "circles", "children": [{"similarity": 0.9999999999999999}]}]}]}, {"name": "VERB", "children": [{"name": "have", "children": [{"name": "have", "children": [{"similarity": 1.0}]}, {"name": "are", "children": [{"similarity": 0.7346809821386662}]}, {"name": "get", "children": [{"similarity": 0.7104161269573481}]}, {"name": "seem", "children": [{"similarity": 0.7208965691265472}]}]}, {"name": "explain", "children": [{"name": "explain", "children": [{"similarity": 0.9999999999999998}]}, {"name": "clarify", "children": [{"similarity": 0.7438380573845715}]}]}, {"name": "eject", "children": [{"name": "eject", "children": [{"similarity": 0.9999999999999999}]}, {"name": "ejecting", "children": [{"similarity": 0.7337622693975142}]}]}, {"name": "clarify", "children": [{"name": "explain", "children": [{"similarity": 0.7438380573845715}]}, {"name": "clarify", "children": [{"similarity": 0.9999999999999999}]}]}, {"name": "returning", "children": [{"name": "return", "children": [{"similarity": 0.7796470100712067}]}, {"name": "returning", "children": [{"similarity": 1.0}]}]}, {"name": "ejecting", "children": [{"name": "eject", "children": [{"similarity": 0.7337622693975142}]}, {"name": "ejecting", "children": [{"similarity": 1.0}]}]}, {"name": "discovered", "children": [{"name": "discovered", "children": [{"similarity": 1.0}]}, {"name": "found", "children": [{"similarity": 0.7510381241454309}]}]}, {"name": "found", "children": [{"name": "discovered", "children": [{"similarity": 0.7510381241454309}]}, {"name": "found", "children": [{"similarity": 1.0}]}]}, {"name": "are", "children": [{"name": "have", "children": [{"similarity": 0.7346809821386662}]}, {"name": "are", "children": [{"similarity": 0.9999999999999997}]}]}, {"name": "do", "children": [{"name": "do", "children": [{"similarity": 1.0}]}, {"name": "seem", "children": [{"similarity": 0.7168131451842321}]}, {"name": "does", "children": [{"similarity": 0.7142621833072444}]}]}, {"name": "get", "children": [{"name": "have", "children": [{"similarity": 0.7104161269573481}]}, {"name": "get", "children": [{"similarity": 1.0}]}]}, {"name": "seem", "children": [{"name": "have", "children": [{"similarity": 0.7208965691265472}]}, {"name": "do", "children": [{"similarity": 0.7168131451842321}]}, {"name": "seem", "children": [{"similarity": 1.0}]}]}, {"name": "does", "children": [{"name": "do", "children": [{"similarity": 0.7142621833072444}]}, {"name": "does", "children": [{"similarity": 1.0000000000000002}]}]}]}, {"name": "ADV_ADJ", "children": [{"name": "alive", "children": [{"name": "alive", "children": [{"similarity": 1.0}]}, {"name": "dead", "children": [{"similarity": 0.7174257226101443}]}]}, {"name": "dead", "children": [{"name": "alive", "children": [{"similarity": 0.7174257226101443}]}, {"name": "dead", "children": [{"similarity": 1.0}]}]}, {"name": "small", "children": [{"name": "small", "children": [{"similarity": 0.9999999999999998}]}, {"name": "smaller", "children": [{"similarity": 0.7731433618791603}]}, {"name": "little", "children": [{"similarity": 0.7017077829277723}]}]}, {"name": "vast", "children": [{"name": "vast", "children": [{"similarity": 0.9999999999999999}]}, {"name": "enormous", "children": [{"similarity": 0.7529430308259598}]}]}, {"name": "intriguing", "children": [{"name": "intriguing", "children": [{"similarity": 1.0}]}, {"name": "captivating", "children": [{"similarity": 0.7391695904404512}]}]}, {"name": "tremendous", "children": [{"name": "tremendous", "children": [{"similarity": 1.0}]}, {"name": "enormous", "children": [{"similarity": 0.7712431748258823}]}]}, {"name": "captivating", "children": [{"name": "intriguing", "children": [{"similarity": 0.7391695904404512}]}, {"name": "captivating", "children": [{"similarity": 0.9999999999999998}]}]}, {"name": "massive", "children": [{"name": "massive", "children": [{"similarity": 0.9999999999999999}]}, {"name": "enormous", "children": [{"similarity": 0.84176436275577}]}]}, {"name": "same", "children": [{"name": "same", "children": [{"similarity": 1.0000000000000002}]}, {"name": "not", "children": [{"similarity": 0.7004245490559413}]}, {"name": "exactly", "children": [{"similarity": 0.702411210401479}]}]}, {"name": "enormous", "children": [{"name": "vast", "children": [{"similarity": 0.7529430308259598}]}, {"name": "tremendous", "children": [{"similarity": 0.7712431748258823}]}, {"name": "massive", "children": [{"similarity": 0.84176436275577}]}, {"name": "enormous", "children": [{"similarity": 1.0000000000000002}]}]}, {"name": "smaller", "children": [{"name": "small", "children": [{"similarity": 0.7731433618791603}]}, {"name": "smaller", "children": [{"similarity": 1.0}]}]}, {"name": "really", "children": [{"name": "really", "children": [{"similarity": 0.9999999999999998}]}, {"name": "not", "children": [{"similarity": 0.7407652914646127}]}, {"name": "exactly", "children": [{"similarity": 0.7482164359832791}]}, {"name": "truly", "children": [{"similarity": 0.7595693145041587}]}, {"name": "way", "children": [{"similarity": 0.7606487473536593}]}, {"name": "too", "children": [{"similarity": 0.8344732064580926}]}, {"name": "well", "children": [{"similarity": 0.7483836793095574}]}]}, {"name": "not", "children": [{"name": "same", "children": [{"similarity": 0.7004245490559413}]}, {"name": "really", "children": [{"similarity": 0.7407652914646127}]}, {"name": "not", "children": [{"similarity": 1.0}]}, {"name": "too", "children": [{"similarity": 0.7369255185654966}]}]}, {"name": "exactly", "children": [{"name": "same", "children": [{"similarity": 0.702411210401479}]}, {"name": "really", "children": [{"similarity": 0.7482164359832791}]}, {"name": "exactly", "children": [{"similarity": 0.9999999999999998}]}, {"name": "precisely", "children": [{"similarity": 0.7454505820858015}]}]}, {"name": "quickly", "children": [{"name": "quickly", "children": [{"similarity": 0.9999999999999998}]}, {"name": "rapidly", "children": [{"similarity": 0.7532367510386178}]}]}, {"name": "truly", "children": [{"name": "really", "children": [{"similarity": 0.7595693145041587}]}, {"name": "truly", "children": [{"similarity": 1.0}]}]}, {"name": "precisely", "children": [{"name": "exactly", "children": [{"similarity": 0.7454505820858015}]}, {"name": "precisely", "children": [{"similarity": 0.9999999999999998}]}]}, {"name": "little", "children": [{"name": "small", "children": [{"similarity": 0.7017077829277723}]}, {"name": "little", "children": [{"similarity": 0.9999999999999999}]}, {"name": "too", "children": [{"similarity": 0.7333647834975289}]}]}, {"name": "rapidly", "children": [{"name": "quickly", "children": [{"similarity": 0.7532367510386178}]}, {"name": "rapidly", "children": [{"similarity": 0.9999999999999998}]}]}, {"name": "Likewise", "children": [{"name": "Likewise", "children": [{"similarity": 1.0000000000000002}]}, {"name": "Moreover", "children": [{"similarity": 0.818090509509434}]}]}, {"name": "too", "children": [{"name": "really", "children": [{"similarity": 0.8344732064580926}]}, {"name": "not", "children": [{"similarity": 0.7369255185654966}]}, {"name": "little", "children": [{"similarity": 0.7333647834975289}]}, {"name": "way", "children": [{"similarity": 0.7103311665539109}]}, {"name": "too", "children": [{"similarity": 0.9999999999999999}]}, {"name": "well", "children": [{"similarity": 0.7569540904208247}]}]}, {"name": "Moreover", "children": [{"name": "Likewise", "children": [{"similarity": 0.818090509509434}]}, {"name": "Moreover", "children": [{"similarity": 1.0000000000000002}]}]}, {"name": "as", "children": [{"name": "as", "children": [{"similarity": 1.0}]}, {"name": "well", "children": [{"similarity": 0.7461969487154666}]}]}, {"name": "well", "children": [{"name": "really", "children": [{"similarity": 0.7483836793095574}]}, {"name": "too", "children": [{"similarity": 0.7569540904208247}]}, {"name": "as", "children": [{"similarity": 0.7461969487154666}]}, {"name": "well", "children": [{"similarity": 1.0}]}]}]}]}]}